{
  "couple": {
    "bride": { "name": "Emma Vanden Berg", "title": "Bride" },
    "groom": { "name": "Caleb Haber", "title": "Groom" }
  },
  "party": [
    {
      "brideSide": { "name": "Jenna VandenBerg", "title": "Maid of Honor", "relationship": "Cousin of the Bride" },
      "groomSide": { "name": "Marcus Hadeed", "title": "Best Man", "relationship": "Cousin of the Groom" }
    },
    {
      "brideSide": { "name": "Hannah Haber", "title": "Bridesmaid", "relationship": "Sister of the Groom" },
      "groomSide": { "name": "Jack Hadeed", "title": "Best Man", "relationship": "Cousin of the Groom" }
    },
    {
      "brideSide": { "name": "Grace Haber", "title": "Bridesmaid", "relationship": "Sister of the Groom" },
      "groomSide": { "name": "Jonathan McIntosh", "title": "Groomsman", "relationship": "Cousin of the Groom" }
    },
    {
      "brideSide": { "name": "Michelle Ameyaw", "title": "Bridesmaid", "relationship": "Childhood friend of the Bride" },
      "groomSide": { "name": "Tom Mygatt", "title": "Groomsman", "relationship": "Childhood friend of the Groom" }
    },
    {
      "brideSide": { "name": "Lizzie Walker", "title": "Bridesmaid", "relationship": "College friend of the Bride" },
      "groomSide": { "name": "Darrel Bossman", "title": "Groomsman", "relationship": "Childhood friend of the Groom" }
    }
  ],
  "officiant": {
    "name": "Sam Hettinger",
    "title": "Senior Pastor of Mount Airy Presbyterian Church"
  },
  "parents": [
    {
      "brideSide": { "name": "Amy Vanden Berg", "title": "Mother of the Bride" },
      "groomSide": { "name": "Kate Haber", "title": "Mother of the Groom" }
    },
    {
      "brideSide": { "name": "Michael Vanden Berg", "title": "Father of the Bride" },
      "groomSide": { "name": "Joseph Haber", "title": "Father of the Groom" }
    }
  ]
}
